pytypegauge/__init__.py
pytypegauge/logger.py
pytypegauge/typegauge.py
pytypegauge-1.0.dist-info/LICENCE.md
pytypegauge-1.0.dist-info/METADATA
pytypegauge-1.0.dist-info/WHEEL
pytypegauge-1.0.dist-info/entry_points.txt
pytypegauge-1.0.dist-info/top_level.txt
pytypegauge-1.0.dist-info/RECORD
