Metadata-Version: 2.1
Name: pytypegauge
Version: 1.0
Summary: A tool to measure the percentage of typed arguments in python functions
Home-page: UNKNOWN
Author: Jules Cassan
Author-email: jules.cassan@hotmail.com
License: UNKNOWN
Project-URL: Github, https://github.com/White-On/pytypegauge
Platform: UNKNOWN
Classifier: Programming Language :: Python :: 3
Classifier: License :: OSI Approved :: MIT License
Classifier: Operating System :: OS Independent
Requires-Python: >=3.8
Requires-Dist: matplotlib >=3.7.5
Requires-Dist: numpy >=1.24.4
Requires-Dist: pandas >=2.0.3
Requires-Dist: rich >=13.7.1
Requires-Dist: tabulate
Provides-Extra: dev
Requires-Dist: black ; extra == 'dev'
Requires-Dist: pre-commit >=3.7.1 ; extra == 'dev'
Requires-Dist: pytest >=8.3.1 ; extra == 'dev'
Requires-Dist: twine >=4.0.2 ; extra == 'dev'
Requires-Dist: wheel ; extra == 'dev'
